turl_project/__init__.py
turl_project/durl_module.py
turbo_url-0.0.1.dist-info/LICENSE
turbo_url-0.0.1.dist-info/METADATA
turbo_url-0.0.1.dist-info/WHEEL
turbo_url-0.0.1.dist-info/top_level.txt
turbo_url-0.0.1.dist-info/RECORD
