Metadata-Version: 2.1
Name: turbo-url
Version: 0.0.1
Summary: download files much faster than curl
Author: shinhwa
Author-email: combwattle@gmail.com
Classifier: Programming Language :: Python :: 3
Classifier: License :: OSI Approved :: Apache Software License
Classifier: Operating System :: OS Independent
Requires-Python: >=3.6
License-File: LICENSE
